celery_singleton/__init__.py
celery_singleton/backends/__init__.py
celery_singleton/backends/base.py
celery_singleton/backends/redis.py
celery_singleton/config.py
celery_singleton/exceptions.py
celery_singleton/singleton.py
celery_singleton/util.py
celery_singleton-0.3.0.dist-info/LICENSE
celery_singleton-0.3.0.dist-info/WHEEL
celery_singleton-0.3.0.dist-info/METADATA
celery_singleton-0.3.0.dist-info/RECORD
